virtualpen/__init__.py
virtualpen-0.1.1.dist-info/LICENCE.txt
virtualpen-0.1.1.dist-info/METADATA
virtualpen-0.1.1.dist-info/WHEEL
virtualpen-0.1.1.dist-info/top_level.txt
virtualpen-0.1.1.dist-info/RECORD
