Metadata-Version: 2.1
Name: virtualpen
Version: 0.1.1
Summary: you can do virtual paints
Home-page: https://github.com/santosh-burada/virtualpen.git
Author: Santosh Burada
Author-email: santu.burada99@gmail.com
License: UNKNOWN
Platform: UNKNOWN
Classifier: Programming Language :: Python :: 3
Classifier: License :: OSI Approved :: MIT License
Classifier: Operating System :: OS Independent
Requires-Python: >=3.6
